arxiv_connections/arxiv_explorer.ipynb
arxiv_connections/arxiv_util.py
arxiv_connections/cli.py
arxiv_connections/graphing.py
arxiv_connections-0.3.0.dist-info/METADATA
arxiv_connections-0.3.0.dist-info/WHEEL
arxiv_connections-0.3.0.dist-info/entry_points.txt
arxiv_connections-0.3.0.dist-info/RECORD
